# 类的初始化，类的实例化，类方法的重写
### 题目
> 代码如下，求运行结果！
```java
public class Father {
    private int i = test();
    private static int j = test2();

    static {
        System.out.print(" 1 ");
    }

    public Father() {
        System.out.print(" 2 ");
    }

    {
        System.out.print(" 3 ");
    }

    public int test() {
        System.out.print(" 4 ");
        return 1;
    }

    public static int test2() {
        System.out.print(" 5 ");
        return 1;
    }
}

public class Son extends Father {
    private int i = test();
    private static int j = test2();

    static {
        System.out.print(" 6 ");
    }

    public Son() {
        System.out.print(" 7 ");
    }

    {
        System.out.print(" 8 ");
    }

    public int test() {
        System.out.print(" 9 ");
        return 1;
    }

    public static int test2() {
        System.out.print(" 10 ");
        return 1;
    }
}

public class Interview1_2 {
    public static void main(String[] args) {
        Son son1=new Son();
        System.out.println("................");
        Son son2=new Son();
    }
}
```
### 分析

##### 类的初始化：
> 1. 子类在初始化时，先执行父类的初始化，再执行子类的初始化。  
> 2. 初始化执行的是字节码中的clinit()方法    
> 3. clinit()方法里面执行的是：     
（1）静态变量的赋值操作.   
（2）静态代码块。   
他们的先后顺序即他们的执行顺序。（静态代码块在前，静态变量赋值在后。执行顺序是：（2），（1）。反之亦然）
> 4. **注意：类的初始化只会执行一遍。**

##### 类的实例化
> 1. 类的实例化其实在执行字节码中的<init>方法
> 2. <init>方法执行的是：
（1）super（）（父类的<init>方法）在构造器中写或者不写super，它都是存在的，
（2）非静态变量赋值和非静态代码块。（执行顺序是他们的先后顺序）
（3）相应参数的构造器
> 3. 每次实例化，都会执行一遍该类的<init>
##### 方法重写
> 非静态方法在调用的时候，其实前面会有一个默认的this，它代表的是正在创建的对象
> 子类如果重写了父类的方法，通过子类对象调用的方法一定是子类重写过的方法。这里是在创建Son对象，所以，父类中执行的test（）方法是子类重写过的test方法
> 哪些方法不会被重写：    
（1）final 方法     
（2）static 方法   
（3）private等在子类中不可见的方法

### 结果
##### 第一遍
1. 父类的初始化：父类的（<clinit>） 5，1 
2. 子类的初始化：子类的（<clinit>） 10 ，6 
3. 父类的实例化：子类的super，即父类的（<init>） 9，3，2 
4. 子类的实例化：子类的（<init>）9，8，7 
##### 第二遍
1. 因为初始化，只用执行一遍。实例化，每次都会执行。
2. 所以第二遍结果为，9 3 2 9 8 7 

### 题目修改一下
```
public class Father {
    {
        System.out.print(" 3 ");
    }
    static {
        System.out.print(" 1 ");
    }
    private int i = test();
    private static int j = test2();
    
    public Father() {
        System.out.print(" 2 ");
    }
    
    private int test() {
        System.out.print(" 4 ");
        return 1;
    }

    public static int test2() {
        System.out.print(" 5 ");
        return 1;
    }
}

 public class Son extends Father {
    private static int j = test2();
    
    public Son() {
        System.out.print(" 7 ");
    }
    {
        System.out.print(" 8 ");
    }
    static {
        System.out.print(" 6 ");
    }

    public int test() {
        System.out.print(" 9 ");
        return 1;
    }
    private int i = test();

    public static int test2() {
        System.out.print(" 10 ");
        return 1;
    }
}
    
    public class Interview1_2 {
    public static void main(String[] args) {
        Father father1=new Father();
        System.out.println("................");
        Son son1=new Son();
        System.out.println("................");
        Father father2=new Father();
        System.out.println("................");
        Son son2=new Son();
    }
}
```

#### 答案：这里涉及到了一个子类不会重写父类的private方法的一个考点
```
        //答案：  1  5  3  4  2 ................
        //        10  6  3  4  2  8  9  7 ................
        //        3  4  2 ................
        //        3  4  2  8  9  7 
```
```
{
  public interview.interview1_2.Son();
    descriptor: ()V
    flags: ACC_PUBLIC
    Code:
      stack=2, locals=1, args_size=1
         0: aload_0
         1: invokespecial #1                  // Method interview/interview1_2/Father."<init>":()V
         4: aload_0
         5: aload_0
         6: invokevirtual #2                  // Method test:()I
         9: putfield      #3                  // Field i:I
        12: getstatic     #4                  // Field java/lang/System.out:Ljava/io/PrintStream;
        15: ldc           #5                  // String  8
        17: invokevirtual #6                  // Method java/io/PrintStream.print:(Ljava/lang/String;
)V
        20: getstatic     #4                  // Field java/lang/System.out:Ljava/io/PrintStream;
        23: ldc           #7                  // String  7
        25: invokevirtual #6                  // Method java/io/PrintStream.print:(Ljava/lang/String;
)V
        28: return
      LineNumberTable:
        line 18: 0
        line 11: 4
        line 23: 12
        line 19: 20
        line 20: 28
      LocalVariableTable:
        Start  Length  Slot  Name   Signature
            0      29     0  this   Linterview/interview1_2/Son;

  public int test();
    descriptor: ()I
    flags: ACC_PUBLIC
    Code:
      stack=2, locals=1, args_size=1
         0: getstatic     #4                  // Field java/lang/System.out:Ljava/io/PrintStream;
         3: ldc           #8                  // String  9
         5: invokevirtual #6                  // Method java/io/PrintStream.print:(Ljava/lang/String;
)V
         8: iconst_1
         9: ireturn
      LineNumberTable:
        line 27: 0
        line 28: 8
      LocalVariableTable:
        Start  Length  Slot  Name   Signature
            0      10     0  this   Linterview/interview1_2/Son;

  public static int test2();
    descriptor: ()I
    flags: ACC_PUBLIC, ACC_STATIC
    Code:
      stack=2, locals=0, args_size=0
         0: getstatic     #4                  // Field java/lang/System.out:Ljava/io/PrintStream;
         3: ldc           #9                  // String  10
         5: invokevirtual #6                  // Method java/io/PrintStream.print:(Ljava/lang/String;
)V
         8: iconst_1
         9: ireturn
      LineNumberTable:
        line 32: 0
        line 33: 8

  static {};
    descriptor: ()V
    flags: ACC_STATIC
    Code:
      stack=2, locals=0, args_size=0
         0: invokestatic  #10                 // Method test2:()I
         3: putstatic     #11                 // Field j:I
         6: getstatic     #4                  // Field java/lang/System.out:Ljava/io/PrintStream;
         9: ldc           #12                 // String  6
        11: invokevirtual #6                  // Method java/io/PrintStream.print:(Ljava/lang/String;
)V
        14: return
      LineNumberTable:
        line 12: 0
        line 15: 6
        line 16: 14
}
SourceFile: "Son.java"

```